{
  "required": true,
  "minVersion": "0.8",
  "package": "com.github.theredbrain.redbrainstweaks.mixin",
  "compatibilityLevel": "JAVA_17",
  "mixins": [
    "block.dispenser.DispenserBehaviorsAccessorMixin",
    "block.sapling.AcaciaSaplingGeneratorMixin",
    "block.sapling.AzaleaSaplingGeneratorMixin",
    "block.sapling.BirchSaplingGeneratorMixin",
    "block.sapling.DarkOakSaplingGeneratorMixin",
    "block.sapling.JungleSaplingGeneratorMixin",
    "block.sapling.OakSaplingGeneratorMixin",
    "block.sapling.SpruceSaplingGeneratorMixin",
    "block.AbstractCauldronBlockInvoker",
    "block.AttachedStemBlockMixin",
    "block.BlocksMixin",
    "block.CactusBlockMixin",
    "block.CampfireBlockMixin",
    "block.CauldronBlockMixin",
    "block.ComposterBlockMixin",
    "block.CropBlockMixin",
    "block.FluidBlockMixin",
    "block.FullComposterInventoryMixin",
    "block.GrassBlockMixin",
    "block.LilyPadBlockMixin",
    "block.MagmaBlockMixin",
    "block.MelonBlockMixin",
    "block.MyceliumBlockMixin",
    "block.NetherWartBlockMixin",
    "block.PlantBlockMixin",
    "block.PointedDripstoneBlockMixin",
    "block.PumpkinBlockMixin",
    "block.SaplingBlockAccessor",
    "block.SaplingBlockMixin",
    "block.StemBlockMixin",
    "block.SugarCaneBlockMixin",
    "client.sound.MusicTypeMixin",
    "enchantment.EnchantmentHelperEnhancementMixin",
    "entity.mob.HuskEntityMixin",
    "entity.mob.MobEntityMixin",
    "entity.mob.SpiderEntityMixin",
    "entity.mob.StrayEntityMixin",
    "entity.mob.ZombieEntityMixin",
    "entity.mob.ZombieVillagerEntityMixin",
    "entity.passive.ChickenEntityMixin",
    "entity.passive.PigEntityMixin",
    "entity.passive.VillagerEntityMixin",
    "entity.player.HungerManagerMixin",
    "entity.player.PlayerEntityMixin",
    "entity.player.PlayerExhaustionAccessorMixin",
    "entity.projectile.thrown.EggEntityMixin",
    "entity.LivingEntityMixin",
    "fluid.LavaFluidMixin",
    "item.AxeItemMixin",
    "item.BucketItemInvoker",
    "item.BucketItemMixin",
    "item.FoodComponentsMixin",
    "item.HoeItemMixin",
    "item.ItemsMixin",
    "item.MiningToolItemMixin",
    "item.PickaxeItemMixin",
    "item.ShovelItemMixin",
    "item.SwordItemMixin",
    "world.PatrolSpawnerMixin",
    "world.WanderingTraderManagerMixin",
    "BootstrapMixin"
  ],
  "injectors": {
    "defaultRequire": 1
  }
}
